{"components":[{"background":"cmr_cls0.png","imageOff":"cmr_cls0.png","x":22,"width":110,"y":391,"type":"button","height":31,"imageOn":"cmr_cls1.png"},{"cellOn":"cmr_sld1.png","markerOn":"none","cellCount":22,"markerOff":"none","background":"cmr_sld0.png","x":67,"width":102,"y":214,"cellOff":"cmr_sld0.png","type":"slider","height":22},{"background":"none","x":38,"width":155,"y":14,"type":"imagebox","height":165},{"background":"cmr_frm.png","x":3,"width":226,"y":5,"type":"imagebox","height":184},{"textHeight":136,"background":"none","textXPos":0,"textYPos":0,"x":24,"width":520,"y":246,"textWidth":520,"type":"textbox","height":136,"font":{"fontFile":"cardsn15.zip"}},{"textHeight":153,"background":"none","textXPos":0,"textYPos":0,"x":248,"width":200,"y":19,"textWidth":200,"type":"textbox","height":153,"font":{"fontFile":"cardsn15.zip"}},{"textHeight":22,"background":"none","textXPos":0,"textYPos":0,"x":19,"width":200,"y":192,"textWidth":200,"type":"textbox","height":22,"font":{"fontFile":"cardsn20.zip"}}],"background":"cmr_bkg.png","x":0,"width":571,"y":0,"type":"container","height":455}