{"components":[{"textHeight":17,"background":"none","textXPos":0,"textYPos":0,"x":52,"width":205,"y":10,"textWidth":205,"type":"textbox","height":17,"font":{"fontFile":"human15.zip"}},{"textHeight":17,"background":"none","textXPos":0,"textYPos":0,"x":296,"width":300,"y":10,"textWidth":300,"type":"textbox","height":17,"font":{"fontFile":"human15.zip"}},{"textHeight":17,"background":"none","textXPos":0,"textYPos":0,"x":598,"width":145,"y":10,"textWidth":145,"type":"textbox","height":17,"font":{"fontFile":"human15.zip"}}],"background":"none","x":0,"width":768,"y":0,"type":"container","height":36}