{"components":[{"background":"hw_yes.png","imageOff":"hw_yes.png","x":0,"width":96,"y":70,"type":"button","height":26,"imageOn":"hw_yeson.png"},{"background":"hw_no.png","imageOff":"hw_no.png","x":0,"width":96,"y":101,"type":"button","height":26,"imageOn":"hw_noon.png"},{"textHeight":102,"background":"none","textXPos":0,"textYPos":0,"x":110,"width":200,"y":30,"textWidth":200,"type":"textbox","height":102,"font":{"fontFile":"human15.zip"}}],"background":"hw_scrn1.png","x":0,"width":400,"y":0,"type":"container","height":165}